gingerino/__init__.py
gingerino/main.py
gingerino-0.1.6.dist-info/METADATA
gingerino-0.1.6.dist-info/WHEEL
gingerino-0.1.6.dist-info/top_level.txt
gingerino-0.1.6.dist-info/RECORD
