Metadata-Version: 2.4
Name: gingerino
Version: 0.1.6
Summary: Parse strings using Jinja-style templates
Author-email: Marco Burro <marcoburro98@gmail.com>
Requires-Python: >=3.11
